Kuat/__init__.py
namirahs-0.1.0.dist-info/METADATA
namirahs-0.1.0.dist-info/WHEEL
namirahs-0.1.0.dist-info/top_level.txt
namirahs-0.1.0.dist-info/RECORD
